{
  "category": "Sealing",
  "itemName": "Caulking Not Complete",
  "children": [
    {
      "type": "PARAGRAPH",
      "children": [
        {
          "text": "The caulking in this area has not yet been completed.",
          "bold": false,
          "italics": false
        }
      ]
    },
    {
      "type": "ITEM_IMAGES_NOTES"
    },
    {
      "type": "PARAGRAPH",
      "children": [
        {
          "text": "",
          "bold": false,
          "italics": false
        }
      ]
    },
    {
      "type": "PARAGRAPH",
      "children": [
        {
          "text": "This caulking must be done to ensure a neat finish that is properly sealed.",
          "bold": false,
          "italics": false
        }
      ]
    }
  ]
}