{
  "category": "Wall Frame",
  "itemName": "Lintel Fixings",
  "children": [
    {
      "type": "PARAGRAPH",
      "children": [
        {
          "text": "There are lintels that have not been adequately nailed to the jamb studs.",
          "bold": false,
          "italics": false
        }
      ]
    },
    {
      "type": "ITEM_IMAGES_NOTES"
    },
    {
      "type": "PARAGRAPH",
      "children": [
        {
          "text": "",
          "bold": false,
          "italics": false
        }
      ]
    },
    {
      "type": "PARAGRAPH",
      "children": [
        {
          "text": "The relevant Australian Standard AS 1684 Residential Timber-Framed Construction requires in section 9.5 Nominal Fixings that lintels are fixed through their jamb studs with at least 2/75mm nails.",
          "bold": false,
          "italics": false
        }
      ]
    },
    {
      "type": "PARAGRAPH",
      "children": [
        {
          "text": "",
          "bold": false,
          "italics": false
        }
      ]
    },
    {
      "type": "PARAGRAPH",
      "children": [
        {
          "text": "Additional nails must be installed into these lintels in accordance with AS 1684.",
          "bold": false,
          "italics": false
        }
      ]
    }
  ]
}