{
  "category": "Waterproofing",
  "itemName": "Waterproofing Upstand",
  "children": [
    {
      "type": "PARAGRAPH",
      "children": [
        {
          "text": "The waterproofing does not extend up the walls at least 25mm above the proposed finished floor level.",
          "bold": false,
          "italics": false
        }
      ]
    },
    {
      "type": "ITEM_IMAGES_NOTES"
    },
    {
      "type": "PARAGRAPH",
      "children": [
        {
          "text": "",
          "bold": false,
          "italics": false
        }
      ]
    },
    {
      "type": "PARAGRAPH",
      "children": [
        {
          "text": "The relevant Australian Standard AS 3740 – Waterproofing of domestic wet areas states in section 3.9.1 Perimeter flashing that",
          "bold": false,
          "italics": false
        },
        {
          "text": "‘Perimeter flashing to wall/floor surfaces shall be continuously sealed to the horizontal surface and have a vertical leg of a minimum of",
          "bold": true,
          "italics": true
        },
        {
          "text": "25 mm above the finished floor level ’ .",
          "bold": true,
          "italics": true,
          "decoration": "underline"
        }
      ]
    },
    {
      "type": "PARAGRAPH",
      "children": [
        {
          "text": "",
          "bold": false,
          "italics": false
        }
      ]
    },
    {
      "type": "PARAGRAPH",
      "children": [
        {
          "text": "The builder must rectify the wall/floor junctions to all of the wet areas of this home as required by the NCC/BCA and the relevant Australian Standard AS 3740.",
          "bold": false,
          "italics": false
        }
      ]
    }
  ]
}